image_exercise/__init__.py
image_exercise/processing/__init__.py
image_exercise/processing/combination.py
image_exercise/processing/transformation.py
image_exercise/utils/__init__.py
image_exercise/utils/io.py
image_exercise/utils/plot.py
image_exercise-0.0.1.dist-info/METADATA
image_exercise-0.0.1.dist-info/WHEEL
image_exercise-0.0.1.dist-info/top_level.txt
image_exercise-0.0.1.dist-info/RECORD
