Metadata-Version: 2.1
Name: image-exercise
Version: 0.0.1
Summary: Test 1 version - Image processing. This project belongs to Karina Tiemi Kato, Tech Lead, Machine Learning Engineer, Data Scientist Specialist at Take. This package is a demo for simulation of upload on the Test Pypi website, and it's from one of the classes from Tech Generation Unimed - BH - Data Science Bootcamp. E-mail:karinatkato@gmail.com
Home-page: https://github.com/tiagotff/DIO/tree/main/Ciencia_de_Dados_Unimed_BH/Modulo_2%20_Python_para_Cientistas_de_Dados/desafios/projeto_criacao_pacotes_processamento_imagens/image-processing-package
Author: Tiago de Freitas Faustino
Author-email: t.faustino91@gmail.com
Requires-Python: >=3.8
Requires-Dist: matplotlib
Requires-Dist: numpy
Requires-Dist: scikit-image (>=0.16.1)
